NightWind3DLib2/Bridge.py
NightWind3DLib2/EnergySaving.py
NightWind3DLib2/HitTheAlien.py
NightWind3DLib2/SolarCar.py
NightWind3DLib2/Stage.py
NightWind3DLib2/TextDisplay.py
NightWind3DLib2/TransformModel.py
NightWind3DLib2/__init__.py
NightWind3DLib2/__pycache__/Bridge.cpython-39.pyc
NightWind3DLib2/__pycache__/EnergySaving.cpython-39.pyc
NightWind3DLib2/__pycache__/HitTheAlien.cpython-39.pyc
NightWind3DLib2/__pycache__/SolarCar.cpython-39.pyc
NightWind3DLib2/__pycache__/Stage.cpython-39.pyc
NightWind3DLib2/__pycache__/TextDisplay.cpython-39.pyc
NightWind3DLib2/__pycache__/TransformModel.cpython-39.pyc
NightWind3DLib2/__pycache__/__init__.cpython-39.pyc
NightWind3DLib2/images_alien/alien_1.egg
NightWind3DLib2/images_alien/alien_2.egg
NightWind3DLib2/images_alien/alien_3.egg
NightWind3DLib2/images_alien/hammer.egg
NightWind3DLib2/images_alien/woodland.egg
NightWind3DLib2/images_alien/texture/WXE-DM.png
NightWind3DLib2/images_alien/texture/WXE-MZ.png
NightWind3DLib2/images_alien/texture/WXE-SM_1.png
NightWind3DLib2/images_alien/texture/WXE-SM_2.png
NightWind3DLib2/images_alien/texture/WXR_1.png
NightWind3DLib2/images_alien/texture/WXR_2.jpg
NightWind3DLib2/images_alien/texture/WXR_2.png
NightWind3DLib2/images_alien/texture/WXR_3.jpg
NightWind3DLib2/images_alien/texture/WXR_3.png
NightWind3DLib2/images_alien/texture/chuizi.png
NightWind3DLib2/images_house/bridge.egg
NightWind3DLib2/images_house/car.egg
NightWind3DLib2/images_house/car_run.egg
NightWind3DLib2/images_house/cliff.egg.pz
NightWind3DLib2/images_house/house.egg
NightWind3DLib2/images_house/lamp.egg
NightWind3DLib2/images_house/scene.egg.pz
NightWind3DLib2/images_house/shelf.egg
NightWind3DLib2/images_house/solar_panel.egg
NightWind3DLib2/images_house/sun.egg.pz
NightWind3DLib2/images_house/texture/00001.png
NightWind3DLib2/images_house/texture/00071.png
NightWind3DLib2/images_house/texture/BarkDecidious0194_1_S.jpg
NightWind3DLib2/images_house/texture/Body01_col_1001.png
NightWind3DLib2-0.1.0.dist-info/METADATA
NightWind3DLib2-0.1.0.dist-info/WHEEL
NightWind3DLib2-0.1.0.dist-info/top_level.txt
NightWind3DLib2-0.1.0.dist-info/RECORD
