Metadata-Version: 2.1
Name: NightWind3DLib2
Version: 0.1.0
Summary: Some little 3D games
Home-page: https://github.com/
Author: Nova_NightWind0311
Author-email: 
License: UNKNOWN
Platform: UNKNOWN
Classifier: Programming Language :: Python :: 3
Classifier: License :: OSI Approved :: MIT License
Classifier: Operating System :: OS Independent
Requires-Dist: panda3d (>=1.10.7)
